nonebot_plugin_hitokoto_plus/__init__.py
nonebot_plugin_hitokoto_plus/api.py
nonebot_plugin_hitokoto_plus/config.py
nonebot_plugin_hitokoto_plus/models.py
nonebot_plugin_hitokoto_plus/rate_limiter.py
nonebot_plugin_hitokoto_plus/handlers/__init__.py
nonebot_plugin_hitokoto_plus/handlers/basic.py
nonebot_plugin_hitokoto_plus/handlers/favorites.py
nonebot_plugin_hitokoto_plus/handlers/help.py
nonebot_plugin_hitokoto_plus-0.3.5.dist-info/METADATA
nonebot_plugin_hitokoto_plus-0.3.5.dist-info/WHEEL
nonebot_plugin_hitokoto_plus-0.3.5.dist-info/licenses/LICENSE
nonebot_plugin_hitokoto_plus-0.3.5.dist-info/RECORD
