Metadata-Version: 2.4
Name: nonebot-plugin-hitokoto-plus
Version: 0.3.5
Summary: （可能是）更好的一言插件！
Project-URL: Homepage, https://github.com/enKl03B/nonebot-plugin-hitokoto-plus
Project-URL: Repository, https://github.com/enKl03B/nonebot-plugin-hitokoto-plus.git
Project-URL: Documentation, https://github.com/enKl03B/nonebot-plugin-hitokoto-plus#readme
Author-email: enKl03B <enKl03B@163.com>
License: MIT
License-File: LICENSE
Requires-Python: >=3.9
Requires-Dist: httpx>=0.23.0
Requires-Dist: nonebot-plugin-alconna>=0.57.2
Requires-Dist: nonebot-plugin-apscheduler>=0.5.0
Requires-Dist: nonebot-plugin-localstore>=0.7.4
Requires-Dist: nonebot-plugin-uninfo>=0.7.3
Requires-Dist: nonebot2>=2.4.2
